source_surveymonkey/__init__.py
source_surveymonkey/components.py
source_surveymonkey/config_migrations.py
source_surveymonkey/manifest.yaml
source_surveymonkey/run.py
source_surveymonkey/schemas/collectors.json
source_surveymonkey/schemas/survey_collectors.json
source_surveymonkey/schemas/survey_ids.json
source_surveymonkey/schemas/survey_pages.json
source_surveymonkey/schemas/survey_questions.json
source_surveymonkey/schemas/survey_responses.json
source_surveymonkey/schemas/surveys.json
source_surveymonkey/source.py
source_surveymonkey/streams.py
airbyte_source_surveymonkey-0.3.47.dist-info/METADATA
airbyte_source_surveymonkey-0.3.47.dist-info/WHEEL
airbyte_source_surveymonkey-0.3.47.dist-info/entry_points.txt
airbyte_source_surveymonkey-0.3.47.dist-info/RECORD
