Metadata-Version: 2.1
Name: airbyte-source-surveymonkey
Version: 0.3.47
Summary: Source implementation for Surveymonkey.
Home-page: https://airbyte.com
License: ELv2
Author: Airbyte
Author-email: contact@airbyte.io
Requires-Python: >=3.9,<3.12
Classifier: License :: Other/Proprietary License
Classifier: Programming Language :: Python :: 3
Classifier: Programming Language :: Python :: 3.9
Classifier: Programming Language :: Python :: 3.10
Classifier: Programming Language :: Python :: 3.11
Requires-Dist: airbyte-cdk (>=2,<3)
Requires-Dist: urllib3 (==1.26.18)
Requires-Dist: vcrpy (==4.1.1)
Project-URL: Documentation, https://docs.airbyte.com/integrations/sources/surveymonkey
Project-URL: Repository, https://github.com/airbytehq/airbyte
